upscalers
