Metadata-Version: 1.2
Name: upscalers
Version: 0.5.3
Summary: AI upscaling of images
Home-page: https://github.com/kmewhort/upscalers
Author: Kent Mewhort
Author-email: kent@openissues.ca
License: UNKNOWN
Platform: UNKNOWN
Requires-Python: >=3.7
